mario_gpt/__init__.py
mario_gpt/dataset.py
mario_gpt/level.py
mario_gpt/prompter.py
mario_gpt/sampler.py
mario_gpt/utils.py
mario_gpt/data/tiles/N.png
mario_gpt/data/tiles/Y.png
mario_gpt/data/tiles/cannon_bottom.png
mario_gpt/data/tiles/cannon_top.png
mario_gpt/data/tiles/flying_koopa.png
mario_gpt/data/tiles/ki-background.png
mario_gpt/data/tiles/ki-door.png
mario_gpt/data/tiles/ki-hazard.png
mario_gpt/data/tiles/ki-moving-platform.png
mario_gpt/data/tiles/ki-passable.png
mario_gpt/data/tiles/ki-path.png
mario_gpt/data/tiles/ki-unpassable.png
mario_gpt/data/tiles/mm-CMM.png
mario_gpt/data/tiles/mm-DMM.png
mario_gpt/data/tiles/mm-HMM.png
mario_gpt/data/tiles/mm-LMM.png
mario_gpt/data/tiles/mm-MMM.png
mario_gpt/data/tiles/mm-TMM.png
mario_gpt/data/tiles/mma_tiles.zip
mario_gpt/data/tiles/plant.png
mario_gpt/data/tiles/smb-background.png
mario_gpt/data/tiles/smb-breakable.png
mario_gpt/data/tiles/smb-coin.png
mario_gpt/data/tiles/smb-enemy.png
mario_gpt/data/tiles/smb-path.png
mario_gpt/data/tiles/smb-question.png
mario_gpt/data/tiles/smb-tube-lower-left.png
mario_gpt/data/tiles/smb-tube-lower-right.png
mario_gpt/data/tiles/smb-tube-top-left.png
mario_gpt/data/tiles/smb-tube-top-right.png
mario_gpt/data/tiles/smb-unpassable.png
mario_gpt/data/tiles/smb_enemies_sheet.png
mario_gpt/data/tiles/tile004 (1).png
mario_gpt/data/tiles/tile004 (2).png
mario_gpt/data/tiles/tile004.png
mario_gpt/lm/__init__.py
mario_gpt/lm/base.py
mario_gpt/lm/bert.py
mario_gpt/lm/gpt.py
mario_gpt/simulator/PlayAstar.jar
mario_gpt/simulator/PlayLevel.jar
mario_gpt/simulator/__init__.py
mario_gpt/simulator/simulator.py
mario_gpt/simulator/img/README.md
mario_gpt/simulator/img/enemysheet.png
mario_gpt/simulator/img/favicon.png
mario_gpt/simulator/img/firemariosheet.png
mario_gpt/simulator/img/font.gif
mario_gpt/simulator/img/frameworkAD.gif
mario_gpt/simulator/img/itemsheet.png
mario_gpt/simulator/img/mapsheet.png
mario_gpt/simulator/img/mariosheet.png
mario_gpt/simulator/img/particlesheet.png
mario_gpt-0.1.3.dist-info/LICENSE
mario_gpt-0.1.3.dist-info/METADATA
mario_gpt-0.1.3.dist-info/WHEEL
mario_gpt-0.1.3.dist-info/top_level.txt
mario_gpt-0.1.3.dist-info/RECORD
