Metadata-Version: 2.1
Name: mario-gpt
Version: 0.1.3
Summary: Generating Mario Levels with GPT2. Code for the paper: 'MarioGPT: Open-Ended Text2Level Generation through Large Language Models', https://arxiv.org/abs/2302.05981
Home-page: https://github.com/shyamsn97/mario-gpt
Author: Shyam Sudhakaran
Author-email: shyamsnair@protonmail.com
License: MIT
Platform: UNKNOWN
Classifier: Development Status :: 2 - Pre-Alpha
Classifier: License :: OSI Approved :: MIT License
Classifier: Programming Language :: Python :: 3
License-File: LICENSE
Requires-Dist: torch
Requires-Dist: transformers
Requires-Dist: scipy
Requires-Dist: tqdm
Requires-Dist: pillow
